dome.py
domedataaccess-1.0.0.dist-info/LICENSE
domedataaccess-1.0.0.dist-info/WHEEL
domedataaccess-1.0.0.dist-info/METADATA
domedataaccess-1.0.0.dist-info/RECORD
